ml3log/__init__.py
ml3log/__main__.py
ml3log/logger.py
ml3log/server.py
ml3log/static/script.js
ml3log/static/styles.css
ml3log/static/viewer.html
ml3log-0.1.1.dist-info/LICENSE
ml3log-0.1.1.dist-info/METADATA
ml3log-0.1.1.dist-info/WHEEL
ml3log-0.1.1.dist-info/entry_points.txt
ml3log-0.1.1.dist-info/top_level.txt
ml3log-0.1.1.dist-info/RECORD
