Metadata-Version: 2.2
Name: ml3log
Version: 0.1.1
Summary: A minimal logger and web server
Author: Multinear
Requires-Python: >=3.8
License-File: LICENSE
Dynamic: author
Dynamic: requires-python
